mahjong_hand_distance/__init__.py
mahjong_hand_distance/tile.py
mahjong_hand_distance/version.py
mahjong_hand_distance-0.0.1.dist-info/LICENSE
mahjong_hand_distance-0.0.1.dist-info/METADATA
mahjong_hand_distance-0.0.1.dist-info/WHEEL
mahjong_hand_distance-0.0.1.dist-info/top_level.txt
mahjong_hand_distance-0.0.1.dist-info/RECORD
